project/__init__.py
basekkk-0.0.0.1.dist-info/METADATA
basekkk-0.0.0.1.dist-info/WHEEL
basekkk-0.0.0.1.dist-info/top_level.txt
basekkk-0.0.0.1.dist-info/RECORD
